nuttx_env/__init__.py
nuttx_env/cli.py
nuttx_env/github.py
nuttx_env/handlers.py
nuttx_env/kconfig.py
nuttx_env/utils.py
nuttx_env/vars.py
nuttx_env-0.2.2.dist-info/METADATA
nuttx_env-0.2.2.dist-info/WHEEL
nuttx_env-0.2.2.dist-info/entry_points.txt
nuttx_env-0.2.2.dist-info/RECORD
